calc4ap/voc.py
calc4ap/libs/__init__.py
calc4ap/libs/calc_ap.py
calc4ap/libs/calc_iou.py
calc4ap/libs/classifiers.py
calc4ap/utils/__init__.py
calc4ap/utils/coco.py
calc4ap-1.0.1.dist-info/LICENSE
calc4ap-1.0.1.dist-info/METADATA
calc4ap-1.0.1.dist-info/WHEEL
calc4ap-1.0.1.dist-info/top_level.txt
calc4ap-1.0.1.dist-info/RECORD
