Metadata-Version: 2.1
Name: calc4ap
Version: 1.0.1
Summary: Easy AP Calculator with Python
Home-page: https://github.com/DevBruce/calc4ap
Author: devbruce
Author-email: bruce93k@gmail.com
License: MIT
Keywords: ap,map,object_detection,pascal_voc,coco,deep_learning,evaluation
Platform: UNKNOWN
Requires-Python: >=3.6.5
